README.md
sqlc_runtime/__init__.py
sqlc_runtime/asyncpg.py
sqlc_runtime/interface.py
sqlc_runtime/psycopg2.py
sqlc_runtime/py.typed
sqlc_python_runtime-1.0.1.dist-info/LICENSE
sqlc_python_runtime-1.0.1.dist-info/WHEEL
sqlc_python_runtime-1.0.1.dist-info/METADATA
sqlc_python_runtime-1.0.1.dist-info/RECORD
