Metadata-Version: 2.1
Name: sqlc-python-runtime
Version: 1.0.1
Summary: Runtime components for code generated by sqlc
Home-page: https://github.com/robholt/sqlc-python-runtime
License: MIT
Author: Robert Holt
Author-email: rholt@datto.com
Requires-Python: >=3.7,<4.0
Classifier: License :: OSI Approved :: MIT License
Classifier: Programming Language :: Python :: 3
Classifier: Programming Language :: Python :: 3.7
Classifier: Programming Language :: Python :: 3.8
Classifier: Programming Language :: Python :: 3.9
Provides-Extra: asyncpg
Provides-Extra: psycopg2
Requires-Dist: asyncpg (>=0.22.0,<0.23.0); extra == "asyncpg"
Requires-Dist: psycopg2-binary (>=2.8.6,<3.0.0); extra == "psycopg2"
Requires-Dist: pydantic (>=1.4,<2.0)
